solvers/__init__.py
solvers/svgcaptcha/__init__.py
solvers/svgcaptcha/solver.py
svg_captcha_solver-0.0.9.dist-info/LICENSE.txt
svg_captcha_solver-0.0.9.dist-info/METADATA
svg_captcha_solver-0.0.9.dist-info/WHEEL
svg_captcha_solver-0.0.9.dist-info/top_level.txt
svg_captcha_solver-0.0.9.dist-info/RECORD
