Metadata-Version: 2.1
Name: svg-captcha-solver
Version: 0.0.9
Summary: svg captcha solver
Home-page: https://github.com/kamisaberi
Author: kamran saberifard
Author-email: kamisaberi@gmail.com
Project-URL: Bug Tracker, https://github.com/kamisaberi
Classifier: Programming Language :: Python :: 3
Classifier: License :: OSI Approved :: MIT License
Classifier: Operating System :: OS Independent
Requires-Python: >=3.10
License-File: LICENSE.txt
